LICENSE
README.md
cli.py
config.py
deye.py
mqtt.py
setup.py
storage.py
deye.egg-info/PKG-INFO
deye.egg-info/SOURCES.txt
deye.egg-info/dependency_links.txt
deye.egg-info/entry_points.txt
deye.egg-info/requires.txt
deye.egg-info/top_level.txt